flt/__init__.py
flt/generic.py
flt/jax.py
flt/numpy.cp314t-win_amd64.pyd
flt-2025.2.1.dist-info/licenses/LICENSE
flt-2025.2.1.dist-info/METADATA
flt-2025.2.1.dist-info/WHEEL
flt-2025.2.1.dist-info/top_level.txt
flt-2025.2.1.dist-info/RECORD
