Metadata-Version: 2.4
Name: flt
Version: 2025.2.1
Summary: Fast Legendre transform for NumPy and JAX
Maintainer-email: Nicolas Tessore <n.tessore@ucl.ac.uk>
License: MIT
Project-URL: Homepage, https://github.com/ntessore/flt
Classifier: Programming Language :: Python :: 3
Classifier: License :: OSI Approved :: MIT License
Classifier: Operating System :: OS Independent
Requires-Python: >=3.9
License-File: LICENSE
Requires-Dist: numpy
Provides-Extra: test
Requires-Dist: pytest; extra == "test"
Requires-Dist: numpy; extra == "test"
Requires-Dist: scipy; extra == "test"
Requires-Dist: jax; extra == "test"
Provides-Extra: doc
Requires-Dist: sphinx; extra == "doc"
Requires-Dist: furo; extra == "doc"
Requires-Dist: sphinxcontrib-katex; extra == "doc"
Requires-Dist: numpydoc; extra == "doc"
Provides-Extra: numpy
Requires-Dist: numpy; extra == "numpy"
Requires-Dist: scipy; extra == "numpy"
Provides-Extra: jax
Requires-Dist: jax; extra == "jax"
Dynamic: license-file
